{
  "inputUrl": "https://www.instagram.com/masihimtiaz_official",
  "id": "41214192661",
  "username": "masihimtiaz_official",
  "url": "https://www.instagram.com/masihimtiaz_official",
  "fullName": "Masih Imtiaz",
  "biography": "The World Through My Lens.                                                                CEO @imtiazdevelopments \nSon. Husband. Dad. Brother. Friend.",
  "externalUrls": [
    {
      "title": "Imtiaz Developments",
      "lynx_url": "https://l.instagram.com/?u=http%3A%2F%2Fwww.imtiaz.ae%2F&e=AUC7jXs3B1KYr5vGnFEwtJ2dWszdtWLBeCq6W_9t7iurQKySs4PGScVcTHXgEswLI4PSxWoY8oP9PF-01l50GgS6t5sqA0CL",
      "url": "http://www.imtiaz.ae",
      "link_type": "external"
    },
    {
      "title": "LinkedIn",
      "lynx_url": "https://l.instagram.com/?u=https%3A%2F%2Fwww.linkedin.com%2Fin%2Fmasih-imtiaz-309541a9%3Futm_source%3Dshare_via%26utm_content%3Dprofile%26utm_medium%3Dmember_ios&e=AUCjbbac6qsxboAm7fLYnyDLRnudMnJJfTKx62kVpfVwCLr-zfk0m_aqE6PQiXJhLkevyNrXtZALGaKcBXvIMwR0YAY7gVB2",
      "url": "https://www.linkedin.com/in/masih-imtiaz-309541a9?utm_source=share_via&utm_content=profile&utm_medium=member_ios",
      "link_type": "external"
    }
  ],
  "externalUrl": "http://www.imtiaz.ae/",
  "externalUrlShimmed": "https://l.instagram.com/?u=http%3A%2F%2Fwww.imtiaz.ae%2F&e=AUD2CUYKJ8rgZSzU1hq24WP_Pr5X4keZqHwLUAwpXeYEPo218n02CAlQ9ZuZx1SbfpN5atArtLMm-yVKMWLLNPdZ2P-MIAGi",
  "followersCount": 8626,
  "followsCount": 18,
  "highlightReelCount": 5,
  "isBusinessAccount": false,
  "joinedRecently": false,
  "businessCategoryName": "Entrepreneur",
  "private": false,
  "verified": true,
  "profilePicUrl": "https://scontent-dfw6-1.cdninstagram.com/v/t51.82787-19/657871041_18066075647368662_6444310050413860249_n.jpg?stp=dst-jpg_e0_s150x150_tt6&efg=eyJ2ZW5jb2RlX3RhZyI6InByb2ZpbGVfcGljLmRqYW5nby4xMDgwLmMyIn0&_nc_ht=scontent-dfw6-1.cdninstagram.com&_nc_cat=106&_nc_oc=Q6cZ2gFSXiroBSjRzB-WEaZ1ZzISmxmHU5fPU6J6gMFS78ccpZxaHTY6GRD0FqUDPOMDVQg&_nc_ohc=8PF-I6RmqLkQ7kNvwGg3wqB&_nc_gid=D-zzd2bJFWa8pLO8E0JTRQ&edm=AOQ1c0wBAAAA&ccb=7-5&oh=00_Af5WDo9swwdLY8A4rNoEVywFFncS4VUySHuF14Id0ZpWAw&oe=6A20566D&_nc_sid=8b3546",
  "profilePicUrlHD": "https://scontent-dfw6-1.cdninstagram.com/v/t51.82787-19/657871041_18066075647368662_6444310050413860249_n.jpg?stp=dst-jpg_s320x320_tt6&efg=eyJ2ZW5jb2RlX3RhZyI6InByb2ZpbGVfcGljLmRqYW5nby4xMDgwLmMyIn0&_nc_ht=scontent-dfw6-1.cdninstagram.com&_nc_cat=106&_nc_oc=Q6cZ2gFSXiroBSjRzB-WEaZ1ZzISmxmHU5fPU6J6gMFS78ccpZxaHTY6GRD0FqUDPOMDVQg&_nc_ohc=8PF-I6RmqLkQ7kNvwGg3wqB&_nc_gid=D-zzd2bJFWa8pLO8E0JTRQ&edm=AOQ1c0wBAAAA&ccb=7-5&oh=00_Af4ckkyWhuA7FbkahA6CS7E7tDO87WZP4KdFKn2OdSb2UA&oe=6A20566D&_nc_sid=8b3546",
  "igtvVideoCount": 0,
  "postsCount": 25,
  "latestPosts": [
    {
      "id": "3901290800263629837",
      "type": "Image",
      "shortCode": "DYkK1AbNowN",
      "caption": "A rare bond beyond business.",
      "url": "https://www.instagram.com/p/DYkK1AbNowN/",
      "commentsCount": 22,
      "dimensionsHeight": 720,
      "dimensionsWidth": 1080,
      "displayUrl": "https://scontent-dfw6-1.cdninstagram.com/v/t51.82787-15/702509177_18077720723368662_7171890352858528286_n.jpg?stp=dst-jpg_e35_s1080x1080_sh2.08_tt6&_nc_ht=scontent-dfw6-1.cdninstagram.com&_nc_cat=106&_nc_oc=Q6cZ2gFSXiroBSjRzB-WEaZ1ZzISmxmHU5fPU6J6gMFS78ccpZxaHTY6GRD0FqUDPOMDVQg&_nc_ohc=RE_MkU9NQwsQ7kNvwG5HTdd&_nc_gid=D-zzd2bJFWa8pLO8E0JTRQ&edm=AOQ1c0wBAAAA&ccb=7-5&ig_cache_key=MzkwMTI5MDgwMDI2MzYyOTgzNw%3D%3D.3-ccb7-5&oh=00_Af4GI2yRE6du_BBOh6_vKqKy-rrqsKc364JQ-b6FZ8B2EQ&oe=6A20478F&_nc_sid=8b3546",
      "likesCount": 785,
      "timestamp": "2026-05-20T15:17:17.000Z",
      "ownerUsername": "masihimtiaz_official",
      "ownerId": "41214192661",
      "isPinned": true,
      "isCommentsDisabled": false
    },
    {
      "id": "3869806731618734853",
      "type": "Image",
      "shortCode": "DW0ULgjjNMF",
      "caption": "Love and respect.",
      "url": "https://www.instagram.com/p/DW0ULgjjNMF/",
      "commentsCount": 51,
      "dimensionsHeight": 1134,
      "dimensionsWidth": 1080,
      "displayUrl": "https://scontent-dfw6-1.cdninstagram.com/v/t51.82787-15/660274074_18069888896368662_1071707479174083339_n.jpg?stp=dst-jpg_e35_p1080x1080_sh2.08_tt6&_nc_ht=scontent-dfw6-1.cdninstagram.com&_nc_cat=106&_nc_oc=Q6cZ2gFSXiroBSjRzB-WEaZ1ZzISmxmHU5fPU6J6gMFS78ccpZxaHTY6GRD0FqUDPOMDVQg&_nc_ohc=JoirQdXmW-4Q7kNvwGJoWXX&_nc_gid=D-zzd2bJFWa8pLO8E0JTRQ&edm=AOQ1c0wBAAAA&ccb=7-5&ig_cache_key=Mzg2OTgwNjczMTYxODczNDg1Mw%3D%3D.3-ccb7-5&oh=00_Af6H9tJttAC6Apg0YsObUeuFmBQPEO9WavibnP70p-zzlA&oe=6A2062B9&_nc_sid=8b3546",
      "likesCount": 1147,
      "timestamp": "2026-04-07T04:43:30.000Z",
      "locationName": "Dubai, United Arab Emirates",
      "locationId": "111070818917271",
      "ownerUsername": "masihimtiaz_official",
      "ownerId": "41214192661",
      "isPinned": true,
      "isCommentsDisabled": false
    },
    {
      "id": "3877396171606214261",
      "type": "Image",
      "shortCode": "DXPR0ZWDEZ1",
      "caption": "𝐈𝐦𝐭𝐢𝐚𝐳 𝐱 𝐇𝐫𝐢𝐭𝐡𝐢𝐤 - A partnership forged in mutual respect, trust and shared standards. \n\n@hrithikroshan @imtiazdevelopments \n\n#ImtiazDevelopments #Collab",
      "hashtags": [
        "ImtiazDevelopments",
        "Collab"
      ],
      "mentions": [
        "hrithikroshan",
        "imtiazdevelopments"
      ],
      "url": "https://www.instagram.com/p/DXPR0ZWDEZ1/",
      "commentsCount": 1196,
      "dimensionsHeight": 1349,
      "dimensionsWidth": 1080,
      "displayUrl": "https://scontent-dfw6-1.cdninstagram.com/v/t51.82787-15/670732150_18071883977368662_1147495305561561882_n.jpg?stp=dst-jpg_e35_p1080x1080_sh2.08_tt6&_nc_ht=scontent-dfw6-1.cdninstagram.com&_nc_cat=106&_nc_oc=Q6cZ2gFSXiroBSjRzB-WEaZ1ZzISmxmHU5fPU6J6gMFS78ccpZxaHTY6GRD0FqUDPOMDVQg&_nc_ohc=MxJX_rQ98bcQ7kNvwHLdbBh&_nc_gid=D-zzd2bJFWa8pLO8E0JTRQ&edm=AOQ1c0wBAAAA&ccb=7-5&ig_cache_key=Mzg3NzM5NjE3MTYwNjIxNDI2MQ%3D%3D.3-ccb7-5&oh=00_Af5-iuwQ5bK1g5kqVUtVoOMBWp2fHCl-NyrXnj3nNfh3Zw&oe=6A205D92&_nc_sid=8b3546",
      "likesCount": 261999,
      "timestamp": "2026-04-17T16:03:29.000Z",
      "locationName": "Imtiaz Developments",
      "locationId": "107676598707070",
      "ownerUsername": "masihimtiaz_official",
      "ownerId": "41214192661",
      "taggedUsers": [
        {
          "full_name": "Hrithik Roshan",
          "id": "414113135",
          "is_verified": true,
          "profile_pic_url": "https://scontent-dfw5-2.cdninstagram.com/v/t51.2885-19/464981437_1562279321329156_8629665658080676907_n.jpg?stp=dst-jpg_e0_s150x150_tt6&efg=eyJ2ZW5jb2RlX3RhZyI6InByb2ZpbGVfcGljLmRqYW5nby4xMDgwLmMyIn0&_nc_ht=scontent-dfw5-2.cdninstagram.com&_nc_cat=1&_nc_oc=Q6cZ2gFSXiroBSjRzB-WEaZ1ZzISmxmHU5fPU6J6gMFS78ccpZxaHTY6GRD0FqUDPOMDVQg&_nc_ohc=0EJA0OrgckoQ7kNvwEOS48S&_nc_gid=D-zzd2bJFWa8pLO8E0JTRQ&edm=AOQ1c0wBAAAA&ccb=7-5&oh=00_Af6Wyk1luqVc9d_l4SFZn7_HxXCkuXoGmNZeu-VNv6f8Kw&oe=6A205DA8&_nc_sid=8b3546",
          "username": "hrithikroshan"
        },
        {
          "full_name": "Imtiaz Developments",
          "id": "54725902033",
          "is_verified": true,
          "profile_pic_url": "https://scontent-dfw6-1.cdninstagram.com/v/t51.2885-19/447880441_1284319319210162_8460718414674929488_n.jpg?stp=dst-jpg_e0_s150x150_tt6&efg=eyJ2ZW5jb2RlX3RhZyI6InByb2ZpbGVfcGljLmRqYW5nby4xMDgwLmMyIn0&_nc_ht=scontent-dfw6-1.cdninstagram.com&_nc_cat=102&_nc_oc=Q6cZ2gFSXiroBSjRzB-WEaZ1ZzISmxmHU5fPU6J6gMFS78ccpZxaHTY6GRD0FqUDPOMDVQg&_nc_ohc=MJPDu0ke9DYQ7kNvwEDVhnH&_nc_gid=D-zzd2bJFWa8pLO8E0JTRQ&edm=AOQ1c0wBAAAA&ccb=7-5&oh=00_Af64WhrafhOCu1hFYeKhp4-7GZeCemH3SXRQP51vjdAjOA&oe=6A20526D&_nc_sid=8b3546",
          "username": "imtiazdevelopments"
        }
      ],
      "isPinned": true,
      "isCommentsDisabled": false
    },
    {
      "id": "3905572823414709146",
      "type": "Sidecar",
      "shortCode": "DYzYcpQDZua",
      "url": "https://www.instagram.com/p/DYzYcpQDZua/",
      "commentsCount": 18,
      "dimensionsHeight": 1440,
      "dimensionsWidth": 1080,
      "displayUrl": "https://scontent-dfw6-1.cdninstagram.com/v/t51.82787-15/708536750_18078646805368662_7737523669452410587_n.jpg?stp=dst-jpg_e35_p1080x1080_sh2.08_tt6&_nc_ht=scontent-dfw6-1.cdninstagram.com&_nc_cat=106&_nc_oc=Q6cZ2gFSXiroBSjRzB-WEaZ1ZzISmxmHU5fPU6J6gMFS78ccpZxaHTY6GRD0FqUDPOMDVQg&_nc_ohc=jnYob_8CjfoQ7kNvwECruJ_&_nc_gid=D-zzd2bJFWa8pLO8E0JTRQ&edm=AOQ1c0wBAAAA&ccb=7-5&ig_cache_key=MzkwNTU3MjIzMzU5NzU5NzA0NQ%3D%3D.3-ccb7-5&oh=00_Af79wvzGUN0IcXFr_u8_q8lUKzpaW8qqAVvBhtaXr2WJyw&oe=6A206B64&_nc_sid=8b3546",
      "images": [
        "https://scontent-dfw6-1.cdninstagram.com/v/t51.82787-15/708536750_18078646805368662_7737523669452410587_n.jpg?stp=dst-jpg_e35_p1080x1080_sh2.08_tt6&_nc_ht=scontent-dfw6-1.cdninstagram.com&_nc_cat=106&_nc_oc=Q6cZ2gFSXiroBSjRzB-WEaZ1ZzISmxmHU5fPU6J6gMFS78ccpZxaHTY6GRD0FqUDPOMDVQg&_nc_ohc=jnYob_8CjfoQ7kNvwECruJ_&_nc_gid=D-zzd2bJFWa8pLO8E0JTRQ&edm=AOQ1c0wBAAAA&ccb=7-5&ig_cache_key=MzkwNTU3MjIzMzU5NzU5NzA0NQ%3D%3D.3-ccb7-5&oh=00_Af79wvzGUN0IcXFr_u8_q8lUKzpaW8qqAVvBhtaXr2WJyw&oe=6A206B64&_nc_sid=8b3546",
        "https://scontent-dfw6-1.cdninstagram.com/v/t51.82787-15/707426877_18078646817368662_6505508325064734395_n.jpg?stp=dst-jpg_e35_p1080x1080_sh2.08_tt6&_nc_ht=scontent-dfw6-1.cdninstagram.com&_nc_cat=106&_nc_oc=Q6cZ2gFSXiroBSjRzB-WEaZ1ZzISmxmHU5fPU6J6gMFS78ccpZxaHTY6GRD0FqUDPOMDVQg&_nc_ohc=fpHxA1MjIkwQ7kNvwF5h0Gi&_nc_gid=D-zzd2bJFWa8pLO8E0JTRQ&edm=AOQ1c0wBAAAA&ccb=7-5&ig_cache_key=MzkwNTU3MjI4NTMyMTYzOTA2OQ%3D%3D.3-ccb7-5&oh=00_Af6Pg-eylkGR8XR3Mn5hK6fHQegOvseW5uWaD8MFc2tg7Q&oe=6A20650A&_nc_sid=8b3546"
      ],
      "likesCount": 595,
      "timestamp": "2026-05-26T13:03:03.000Z",
      "childPosts": [
        {
          "id": "3905572233597597045",
          "type": "Image",
          "shortCode": "DYzYUD8NrV1",
          "url": "https://www.instagram.com/p/DYzYUD8NrV1/",
          "commentsCount": 0,
          "dimensionsHeight": 1440,
          "dimensionsWidth": 1080,
          "displayUrl": "https://scontent-dfw6-1.cdninstagram.com/v/t51.82787-15/708536750_18078646805368662_7737523669452410587_n.jpg?stp=dst-jpg_e35_p1080x1080_sh2.08_tt6&_nc_ht=scontent-dfw6-1.cdninstagram.com&_nc_cat=106&_nc_oc=Q6cZ2gFSXiroBSjRzB-WEaZ1ZzISmxmHU5fPU6J6gMFS78ccpZxaHTY6GRD0FqUDPOMDVQg&_nc_ohc=jnYob_8CjfoQ7kNvwECruJ_&_nc_gid=D-zzd2bJFWa8pLO8E0JTRQ&edm=AOQ1c0wBAAAA&ccb=7-5&ig_cache_key=MzkwNTU3MjIzMzU5NzU5NzA0NQ%3D%3D.3-ccb7-5&oh=00_Af79wvzGUN0IcXFr_u8_q8lUKzpaW8qqAVvBhtaXr2WJyw&oe=6A206B64&_nc_sid=8b3546",
          "ownerUsername": "masihimtiaz_official",
          "ownerId": "41214192661"
        },
        {
          "id": "3905572285321639069",
          "type": "Image",
          "shortCode": "DYzYU0HNPSd",
          "url": "https://www.instagram.com/p/DYzYU0HNPSd/",
          "commentsCount": 0,
          "dimensionsHeight": 1440,
          "dimensionsWidth": 1080,
          "displayUrl": "https://scontent-dfw6-1.cdninstagram.com/v/t51.82787-15/707426877_18078646817368662_6505508325064734395_n.jpg?stp=dst-jpg_e35_p1080x1080_sh2.08_tt6&_nc_ht=scontent-dfw6-1.cdninstagram.com&_nc_cat=106&_nc_oc=Q6cZ2gFSXiroBSjRzB-WEaZ1ZzISmxmHU5fPU6J6gMFS78ccpZxaHTY6GRD0FqUDPOMDVQg&_nc_ohc=fpHxA1MjIkwQ7kNvwF5h0Gi&_nc_gid=D-zzd2bJFWa8pLO8E0JTRQ&edm=AOQ1c0wBAAAA&ccb=7-5&ig_cache_key=MzkwNTU3MjI4NTMyMTYzOTA2OQ%3D%3D.3-ccb7-5&oh=00_Af6Pg-eylkGR8XR3Mn5hK6fHQegOvseW5uWaD8MFc2tg7Q&oe=6A20650A&_nc_sid=8b3546",
          "ownerUsername": "masihimtiaz_official",
          "ownerId": "41214192661"
        }
      ],
      "ownerUsername": "masihimtiaz_official",
      "ownerId": "41214192661",
      "isCommentsDisabled": false
    },
    {
      "id": "3902706506653901854",
      "type": "Video",
      "shortCode": "DYpMuPvtiQe",
      "caption": "The champion.",
      "url": "https://www.instagram.com/p/DYpMuPvtiQe/",
      "commentsCount": 37,
      "dimensionsHeight": 1920,
      "dimensionsWidth": 1080,
      "displayUrl": "https://scontent-dfw6-1.cdninstagram.com/v/t51.82787-15/703752359_18078024764368662_2548669968238092358_n.jpg?stp=dst-jpg_e15_fr_p1080x1080_tt6&_nc_ht=scontent-dfw6-1.cdninstagram.com&_nc_cat=106&_nc_oc=Q6cZ2gFSXiroBSjRzB-WEaZ1ZzISmxmHU5fPU6J6gMFS78ccpZxaHTY6GRD0FqUDPOMDVQg&_nc_ohc=Miahp_NrMNEQ7kNvwFqriNr&_nc_gid=D-zzd2bJFWa8pLO8E0JTRQ&edm=AOQ1c0wBAAAA&ccb=7-5&oh=00_Af6nXt_sX05NWuwGKsdDSjZvzlDm6kgYO6RQqE_736Tdgg&oe=6A205068&_nc_sid=8b3546",
      "videoUrl": "https://scontent-dfw5-1.cdninstagram.com/o1/v/t2/f2/m86/AQPoetC8JIpFjM1cYfKta6unYqrUFIOMOb9NLZGrAZAAyQ3PFNF15XT2_LMDopEIvT5oBuhemMx8_SelJeTgfb5sFFMr6uRdghtcv9k.mp4?_nc_cat=105&_nc_sid=5e9851&_nc_ht=scontent-dfw5-1.cdninstagram.com&_nc_ohc=aCw_tPIHgK4Q7kNvwHR4UOE&efg=eyJ2ZW5jb2RlX3RhZyI6Inhwdl9wcm9ncmVzc2l2ZS5JTlNUQUdSQU0uQ0xJUFMuQzMuNzIwLmRhc2hfYmFzZWxpbmVfMV92MSIsInhwdl9hc3NldF9pZCI6OTk3MTYyMDg5NDUyMzE3LCJhc3NldF9hZ2VfZGF5cyI6NywidmlfdXNlY2FzZV9pZCI6MTAwOTksImR1cmF0aW9uX3MiOjMzLCJ1cmxnZW5fc291cmNlIjoid3d3In0%3D&ccb=17-1&vs=23815220a1ea6ebc&_nc_vs=HBksFQIYUmlnX3hwdl9yZWVsc19wZXJtYW5lbnRfc3JfcHJvZC81MzQ0OUJEMzM4QUEyMEEyMEMwMjVBMTRERkQzRDA4RF92aWRlb19kYXNoaW5pdC5tcDQVAALIARIAFQIYUWlnX3hwdl9wbGFjZW1lbnRfcGVybWFuZW50X3YyL0Y5NDk4OUQyRkI3MTk2OTgwRkQ5QTQyNjM0MzAxMEI4X2F1ZGlvX2Rhc2hpbml0Lm1wNBUCAsgBEgAoABgAGwKIB3VzZV9vaWwBMRJwcm9ncmVzc2l2ZV9yZWNpcGUBMRUAACa6zIDCvLrFAxUCKAJDMywXQECMzMzMzM0YEmRhc2hfYmFzZWxpbmVfMV92MREAdf4HZeadAQA&_nc_gid=D-zzd2bJFWa8pLO8E0JTRQ&_nc_zt=28&_nc_ss=7a3ba&oh=00_Af7o98rjd-IW7M7nqVO8im82xRpM7Jbu1jtCS-ARjoqVCQ&oe=6A1C518E",
      "likesCount": 564,
      "videoViewCount": 54807,
      "timestamp": "2026-05-22T14:09:12.000Z",
      "locationName": "Grand Hyatt Dubai",
      "locationId": "46146807",
      "ownerUsername": "masihimtiaz_official",
      "ownerId": "41214192661",
      "productType": "clips",
      "taggedUsers": [
        {
          "full_name": "Хабиб Нурмагомедов",
          "id": "271229086",
          "is_verified": true,
          "profile_pic_url": "https://scontent-dfw5-2.cdninstagram.com/v/t51.2885-19/458967839_859864559573494_8578259726462253849_n.jpg?stp=dst-jpg_e0_s150x150_tt6&efg=eyJ2ZW5jb2RlX3RhZyI6InByb2ZpbGVfcGljLmRqYW5nby4xMDgwLmMyIn0&_nc_ht=scontent-dfw5-2.cdninstagram.com&_nc_cat=1&_nc_oc=Q6cZ2gFSXiroBSjRzB-WEaZ1ZzISmxmHU5fPU6J6gMFS78ccpZxaHTY6GRD0FqUDPOMDVQg&_nc_ohc=u25_Bu_DEf4Q7kNvwGHqzwH&_nc_gid=D-zzd2bJFWa8pLO8E0JTRQ&edm=AOQ1c0wBAAAA&ccb=7-5&oh=00_Af4xK8qovt7uz-a7X7m4DyaPOE73QEGNr0_qRCHi_A8UDA&oe=6A204B85&_nc_sid=8b3546",
          "username": "khabib_nurmagomedov"
        }
      ],
      "isCommentsDisabled": false
    },
    {
      "id": "3897630392877102642",
      "type": "Video",
      "shortCode": "DYXKjEZNLYy",
      "caption": "A moment worth celebrating.",
      "url": "https://www.instagram.com/p/DYXKjEZNLYy/",
      "commentsCount": 9,
      "dimensionsHeight": 1920,
      "dimensionsWidth": 1080,
      "displayUrl": "https://scontent-dfw6-1.cdninstagram.com/v/t51.82787-15/701756528_18076925105368662_9089035005362837495_n.jpg?stp=dst-jpg_e35_p1080x1080_sh2.08_tt6&_nc_ht=scontent-dfw6-1.cdninstagram.com&_nc_cat=106&_nc_oc=Q6cZ2gFSXiroBSjRzB-WEaZ1ZzISmxmHU5fPU6J6gMFS78ccpZxaHTY6GRD0FqUDPOMDVQg&_nc_ohc=oXaTiQu7XFUQ7kNvwG0kddZ&_nc_gid=D-zzd2bJFWa8pLO8E0JTRQ&edm=AOQ1c0wBAAAA&ccb=7-5&oh=00_Af4dh8zTqoHaGLNmd_ORXHkmX3zFmZJx8SFibuTHpFCe8Q&oe=6A206CC3&_nc_sid=8b3546",
      "videoUrl": "https://scontent-dfw5-1.cdninstagram.com/o1/v/t2/f2/m86/AQPGdodMkPLeFf8NTFWDbAys8w1oU7v9Fg-7j4od2ua2ZNhl7NHInoZQa6rV1sx4P5lc05c9GEiQjVLTFbSjxqBfXWZmSqtVd8hfhP0.mp4?_nc_cat=111&_nc_sid=5e9851&_nc_ht=scontent-dfw5-1.cdninstagram.com&_nc_ohc=o5QCXHwnVCkQ7kNvwF6qfxN&efg=eyJ2ZW5jb2RlX3RhZyI6Inhwdl9wcm9ncmVzc2l2ZS5JTlNUQUdSQU0uQ0xJUFMuQzMuNzIwLmRhc2hfYmFzZWxpbmVfMV92MSIsInhwdl9hc3NldF9pZCI6NDMzMjE0Mjk3MDMzMTA2MCwiYXNzZXRfYWdlX2RheXMiOjE0LCJ2aV91c2VjYXNlX2lkIjoxMDA5OSwiZHVyYXRpb25fcyI6MzIsInVybGdlbl9zb3VyY2UiOiJ3d3cifQ%3D%3D&ccb=17-1&vs=efb1e60717257ad6&_nc_vs=HBksFQIYUmlnX3hwdl9yZWVsc19wZXJtYW5lbnRfc3JfcHJvZC8wNjQ1QTdDMDM5RTNCNDFFNzJENTg4OUE0M0Q3MEZBNV92aWRlb19kYXNoaW5pdC5tcDQVAALIARIAFQIYUWlnX3hwdl9wbGFjZW1lbnRfcGVybWFuZW50X3YyLzQwNDZFQjZGRDJDOUUzRkM4MzVENDkwNzA3QzdDMEFDX2F1ZGlvX2Rhc2hpbml0Lm1wNBUCAsgBEgAoABgAGwKIB3VzZV9vaWwBMRJwcm9ncmVzc2l2ZV9yZWNpcGUBMRUAACbo_uat9IOyDxUCKAJDMywXQEBAAAAAAAAYEmRhc2hfYmFzZWxpbmVfMV92MREAdf4HZeadAQA&_nc_gid=D-zzd2bJFWa8pLO8E0JTRQ&_nc_zt=28&_nc_ss=7a3ba&oh=00_Af7d1F_xuLcA186oXrESQLFEhIj6FVwXQflufG-mX0FhGw&oe=6A1C5264",
      "likesCount": 289,
      "videoViewCount": 10779,
      "timestamp": "2026-05-15T14:12:44.000Z",
      "locationName": "Sakhalin Dubai",
      "locationId": "437187552821071",
      "ownerUsername": "masihimtiaz_official",
      "ownerId": "41214192661",
      "productType": "clips",
      "isCommentsDisabled": false
    },
    {
      "id": "3895916933659294764",
      "type": "Image",
      "shortCode": "DYRE89JMPws",
      "caption": "The best memories are made of simple moments",
      "url": "https://www.instagram.com/p/DYRE89JMPws/",
      "commentsCount": 22,
      "dimensionsHeight": 810,
      "dimensionsWidth": 1080,
      "displayUrl": "https://scontent-dfw6-1.cdninstagram.com/v/t51.82787-15/696279085_18076560161368662_7639913969024572097_n.jpg?stp=dst-jpg_e35_s1080x1080_sh2.08_tt6&_nc_ht=scontent-dfw6-1.cdninstagram.com&_nc_cat=106&_nc_oc=Q6cZ2gFSXiroBSjRzB-WEaZ1ZzISmxmHU5fPU6J6gMFS78ccpZxaHTY6GRD0FqUDPOMDVQg&_nc_ohc=c7og9mvC1ZEQ7kNvwGvfoe_&_nc_gid=D-zzd2bJFWa8pLO8E0JTRQ&edm=AOQ1c0wBAAAA&ccb=7-5&ig_cache_key=Mzg5NTkxNjkzMzY1OTI5NDc2NA%3D%3D.3-ccb7-5&oh=00_Af7wnqfIMnemB7uo-nr8vw4GvbLEQ7G_uYBojfFodgcDTQ&oe=6A203CC5&_nc_sid=8b3546",
      "likesCount": 664,
      "timestamp": "2026-05-13T05:21:40.000Z",
      "ownerUsername": "masihimtiaz_official",
      "ownerId": "41214192661",
      "isCommentsDisabled": false
    },
    {
      "id": "3892558173017864455",
      "type": "Video",
      "shortCode": "DYFJQjiRfkH",
      "caption": "The Symphony by Imtiaz: a landmark in making.",
      "url": "https://www.instagram.com/p/DYFJQjiRfkH/",
      "commentsCount": 16,
      "dimensionsHeight": 1918,
      "dimensionsWidth": 1080,
      "displayUrl": "https://scontent-dfw6-1.cdninstagram.com/v/t51.82787-15/688074634_18075827540368662_1667818661765570580_n.jpg?stp=dst-jpg_e15_tt6&_nc_ht=scontent-dfw6-1.cdninstagram.com&_nc_cat=106&_nc_oc=Q6cZ2gFSXiroBSjRzB-WEaZ1ZzISmxmHU5fPU6J6gMFS78ccpZxaHTY6GRD0FqUDPOMDVQg&_nc_ohc=GVp-ThubVesQ7kNvwHjPwwA&_nc_gid=D-zzd2bJFWa8pLO8E0JTRQ&edm=AOQ1c0wBAAAA&ccb=7-5&oh=00_Af6TzOdsrJxhldil8MxHVcWbbwdI2fEiUxMNsGrHmFbsQg&oe=6A205593&_nc_sid=8b3546",
      "videoUrl": "https://scontent-dfw6-1.cdninstagram.com/o1/v/t2/f2/m86/AQM5eWmfhcwbPT5btX26tfD1a-K-qev8-V7gQR08YfgGvn8WLAIK3FqQCVhmYba4RSEhzxBj2LVUFzXUJGUTpPZ5_dZ0uNiiCvx2eR4.mp4?_nc_cat=102&_nc_sid=5e9851&_nc_ht=scontent-dfw6-1.cdninstagram.com&_nc_ohc=FmJkg6UT-NIQ7kNvwF6ylNp&efg=eyJ2ZW5jb2RlX3RhZyI6Inhwdl9wcm9ncmVzc2l2ZS5JTlNUQUdSQU0uQ0xJUFMuQzMuNzIwLmRhc2hfYmFzZWxpbmVfMV92MSIsInhwdl9hc3NldF9pZCI6ODc0MTU1NzYyMzcxMTQzLCJhc3NldF9hZ2VfZGF5cyI6MjEsInZpX3VzZWNhc2VfaWQiOjEwMDk5LCJkdXJhdGlvbl9zIjozMiwidXJsZ2VuX3NvdXJjZSI6Ind3dyJ9&ccb=17-1&vs=3e01098852ed4fa6&_nc_vs=HBksFQIYUmlnX3hwdl9yZWVsc19wZXJtYW5lbnRfc3JfcHJvZC9BRjQwN0VBNkQ1NzY1RUFCMkUzMjU0MjdFRTg3Qjg4Rl92aWRlb19kYXNoaW5pdC5tcDQVAALIARIAFQIYUWlnX3hwdl9wbGFjZW1lbnRfcGVybWFuZW50X3YyLzM3NDE2MjFEMTQxRDM1REFDMEU4MTA5M0RCRkEwRDlBX2F1ZGlvX2Rhc2hpbml0Lm1wNBUCAsgBEgAoABgAGwKIB3VzZV9vaWwBMRJwcm9ncmVzc2l2ZV9yZWNpcGUBMRUAACaOqY77x8KNAxUCKAJDMywXQEBzMzMzMzMYEmRhc2hfYmFzZWxpbmVfMV92MREAdf4HZeadAQA&_nc_gid=D-zzd2bJFWa8pLO8E0JTRQ&_nc_zt=28&_nc_ss=7a3ba&oh=00_Af4dbScTsVkbx49WePYMNPiahSwwznSrAH7E6kMGrH2k1A&oe=6A1C4B37",
      "likesCount": 499,
      "videoViewCount": 21353,
      "timestamp": "2026-05-08T14:05:00.000Z",
      "locationName": "Coca Cola Arena Dubai",
      "locationId": "101446231237381",
      "ownerUsername": "masihimtiaz_official",
      "ownerId": "41214192661",
      "productType": "clips",
      "taggedUsers": [
        {
          "full_name": "Hrithik Roshan",
          "id": "414113135",
          "is_verified": true,
          "profile_pic_url": "https://scontent-dfw5-2.cdninstagram.com/v/t51.2885-19/464981437_1562279321329156_8629665658080676907_n.jpg?stp=dst-jpg_e0_s150x150_tt6&efg=eyJ2ZW5jb2RlX3RhZyI6InByb2ZpbGVfcGljLmRqYW5nby4xMDgwLmMyIn0&_nc_ht=scontent-dfw5-2.cdninstagram.com&_nc_cat=1&_nc_oc=Q6cZ2gFSXiroBSjRzB-WEaZ1ZzISmxmHU5fPU6J6gMFS78ccpZxaHTY6GRD0FqUDPOMDVQg&_nc_ohc=0EJA0OrgckoQ7kNvwEOS48S&_nc_gid=D-zzd2bJFWa8pLO8E0JTRQ&edm=AOQ1c0wBAAAA&ccb=7-5&oh=00_Af6Wyk1luqVc9d_l4SFZn7_HxXCkuXoGmNZeu-VNv6f8Kw&oe=6A205DA8&_nc_sid=8b3546",
          "username": "hrithikroshan"
        },
        {
          "full_name": "Imtiaz Developments",
          "id": "54725902033",
          "is_verified": true,
          "profile_pic_url": "https://scontent-dfw6-1.cdninstagram.com/v/t51.2885-19/447880441_1284319319210162_8460718414674929488_n.jpg?stp=dst-jpg_e0_s150x150_tt6&efg=eyJ2ZW5jb2RlX3RhZyI6InByb2ZpbGVfcGljLmRqYW5nby4xMDgwLmMyIn0&_nc_ht=scontent-dfw6-1.cdninstagram.com&_nc_cat=102&_nc_oc=Q6cZ2gFSXiroBSjRzB-WEaZ1ZzISmxmHU5fPU6J6gMFS78ccpZxaHTY6GRD0FqUDPOMDVQg&_nc_ohc=MJPDu0ke9DYQ7kNvwEDVhnH&_nc_gid=D-zzd2bJFWa8pLO8E0JTRQ&edm=AOQ1c0wBAAAA&ccb=7-5&oh=00_Af64WhrafhOCu1hFYeKhp4-7GZeCemH3SXRQP51vjdAjOA&oe=6A20526D&_nc_sid=8b3546",
          "username": "imtiazdevelopments"
        }
      ],
      "isCommentsDisabled": false
    },
    {
      "id": "3891104663918284582",
      "type": "Video",
      "shortCode": "DX_-xNstw8m",
      "caption": "Thank you @forbesmiddleeast for the recognition.\n\nCongratulations to all leaders, may we continue to inspire and create impact.",
      "mentions": [
        "forbesmiddleeast"
      ],
      "url": "https://www.instagram.com/p/DX_-xNstw8m/",
      "commentsCount": 40,
      "dimensionsHeight": 1136,
      "dimensionsWidth": 640,
      "displayUrl": "https://scontent-dfw5-1.cdninstagram.com/v/t51.71878-15/685119295_1607971600321595_2516451761553526446_n.jpg?stp=dst-jpg_e15_tt6&_nc_ht=scontent-dfw5-1.cdninstagram.com&_nc_cat=111&_nc_oc=Q6cZ2gFSXiroBSjRzB-WEaZ1ZzISmxmHU5fPU6J6gMFS78ccpZxaHTY6GRD0FqUDPOMDVQg&_nc_ohc=vPLTdPiwHd0Q7kNvwFMUay8&_nc_gid=D-zzd2bJFWa8pLO8E0JTRQ&edm=AOQ1c0wBAAAA&ccb=7-5&oh=00_Af6d9ogdVkigOdMZpcz5M_QJNiQbGdvS4GGnytZSp7NcAQ&oe=6A204A75&_nc_sid=8b3546",
      "videoUrl": "https://scontent-dfw5-2.cdninstagram.com/o1/v/t2/f2/m86/AQPGzBKCVJ9vTNf_l9u2N8cwlsKnGKIOGVDeGCf8VjPFWwEtXOHc_TEWtL263OEeYacGiM8a3kVuECQNnbDkknG62AYizSzte_4OOJo.mp4?_nc_cat=100&_nc_sid=5e9851&_nc_ht=scontent-dfw5-2.cdninstagram.com&_nc_ohc=AJlZFF70BUcQ7kNvwF-tE67&efg=eyJ2ZW5jb2RlX3RhZyI6Inhwdl9wcm9ncmVzc2l2ZS5JTlNUQUdSQU0uQ0xJUFMuQzMuNzIwLmRhc2hfYmFzZWxpbmVfMV92MSIsInhwdl9hc3NldF9pZCI6OTYzNTAzMzQyOTkwNzg2LCJhc3NldF9hZ2VfZGF5cyI6MjMsInZpX3VzZWNhc2VfaWQiOjEwMDk5LCJkdXJhdGlvbl9zIjoxNCwidXJsZ2VuX3NvdXJjZSI6Ind3dyJ9&ccb=17-1&vs=a2255c2789e6e222&_nc_vs=HBksFQIYUmlnX3hwdl9yZWVsc19wZXJtYW5lbnRfc3JfcHJvZC81RjQ4QzRGOTZDMjFBQkZERjIyMTk1NUM1NDkxMEU4Nl92aWRlb19kYXNoaW5pdC5tcDQVAALIARIAFQIYUWlnX3hwdl9wbGFjZW1lbnRfcGVybWFuZW50X3YyL0Y5NDYyNTUyQTJEN0EwNjY0M0RGRTBDRjIzRDY2MUI3X2F1ZGlvX2Rhc2hpbml0Lm1wNBUCAsgBEgAoABgAGwKIB3VzZV9vaWwBMRJwcm9ncmVzc2l2ZV9yZWNpcGUBMRUAACaE1_2no5O2AxUCKAJDMywXQCwAAAAAAAAYEmRhc2hfYmFzZWxpbmVfMV92MREAdf4HZeadAQA&_nc_gid=D-zzd2bJFWa8pLO8E0JTRQ&_nc_zt=28&_nc_ss=7a3ba&oh=00_Af5PZOe8v_qvQvicVWyLH8z1z-tDp_GaFA4nNDnMDlkbjw&oe=6A1C6951",
      "likesCount": 424,
      "videoViewCount": 27820,
      "timestamp": "2026-05-06T13:59:01.000Z",
      "locationName": "Dubai, United Arab Emirates",
      "locationId": "111070818917271",
      "ownerUsername": "masihimtiaz_official",
      "ownerId": "41214192661",
      "productType": "clips",
      "taggedUsers": [
        {
          "full_name": "Forbes Middle East",
          "id": "1544565637",
          "is_verified": true,
          "profile_pic_url": "https://scontent-dfw6-1.cdninstagram.com/v/t51.82787-19/652821443_18570906235053638_9074278463882429886_n.jpg?stp=dst-jpg_e0_s150x150_tt6&efg=eyJ2ZW5jb2RlX3RhZyI6InByb2ZpbGVfcGljLmRqYW5nby4xMDgwLmMyIn0&_nc_ht=scontent-dfw6-1.cdninstagram.com&_nc_cat=102&_nc_oc=Q6cZ2gFSXiroBSjRzB-WEaZ1ZzISmxmHU5fPU6J6gMFS78ccpZxaHTY6GRD0FqUDPOMDVQg&_nc_ohc=lv4bY-5YP2cQ7kNvwHlhhUC&_nc_gid=D-zzd2bJFWa8pLO8E0JTRQ&edm=AOQ1c0wBAAAA&ccb=7-5&oh=00_Af4pjF4c2fKzCBLOjlEHsB5cq3sRWY-CQ2nhLdg1xZg9FQ&oe=6A203643&_nc_sid=8b3546",
          "username": "forbesmiddleeast"
        },
        {
          "full_name": "Imtiaz Developments",
          "id": "54725902033",
          "is_verified": true,
          "profile_pic_url": "https://scontent-dfw6-1.cdninstagram.com/v/t51.2885-19/447880441_1284319319210162_8460718414674929488_n.jpg?stp=dst-jpg_e0_s150x150_tt6&efg=eyJ2ZW5jb2RlX3RhZyI6InByb2ZpbGVfcGljLmRqYW5nby4xMDgwLmMyIn0&_nc_ht=scontent-dfw6-1.cdninstagram.com&_nc_cat=102&_nc_oc=Q6cZ2gFSXiroBSjRzB-WEaZ1ZzISmxmHU5fPU6J6gMFS78ccpZxaHTY6GRD0FqUDPOMDVQg&_nc_ohc=MJPDu0ke9DYQ7kNvwEDVhnH&_nc_gid=D-zzd2bJFWa8pLO8E0JTRQ&edm=AOQ1c0wBAAAA&ccb=7-5&oh=00_Af64WhrafhOCu1hFYeKhp4-7GZeCemH3SXRQP51vjdAjOA&oe=6A20526D&_nc_sid=8b3546",
          "username": "imtiazdevelopments"
        }
      ],
      "isCommentsDisabled": false
    },
    {
      "id": "3890139058138388245",
      "type": "Image",
      "shortCode": "DX8jNzPNhcV",
      "caption": "No one has ever become poor by giving. HH Mohammed bin Rashid Al Maktoum Global Initiatives",
      "url": "https://www.instagram.com/p/DX8jNzPNhcV/",
      "commentsCount": 14,
      "dimensionsHeight": 720,
      "dimensionsWidth": 1080,
      "displayUrl": "https://scontent-dfw6-1.cdninstagram.com/v/t51.82787-15/684630218_18075289781368662_3014870914053889467_n.jpg?stp=dst-jpg_e35_s1080x1080_sh2.08_tt6&_nc_ht=scontent-dfw6-1.cdninstagram.com&_nc_cat=106&_nc_oc=Q6cZ2gFSXiroBSjRzB-WEaZ1ZzISmxmHU5fPU6J6gMFS78ccpZxaHTY6GRD0FqUDPOMDVQg&_nc_ohc=iG_G5dy3tyAQ7kNvwGCph7x&_nc_gid=D-zzd2bJFWa8pLO8E0JTRQ&edm=AOQ1c0wBAAAA&ccb=7-5&ig_cache_key=Mzg5MDEzOTA1ODEzODM4ODI0NQ%3D%3D.3-ccb7-5&oh=00_Af51fSK3x_eFvR5POCqvn-NxcDI7hmEw0VC_yqYQcybuHw&oe=6A2067B2&_nc_sid=8b3546",
      "likesCount": 493,
      "timestamp": "2026-05-05T05:59:50.000Z",
      "ownerUsername": "masihimtiaz_official",
      "ownerId": "41214192661",
      "isCommentsDisabled": false
    },
    {
      "id": "3888203249621146336",
      "type": "Video",
      "shortCode": "DX1rEFEMBrg",
      "caption": "Every move, towards glory.",
      "url": "https://www.instagram.com/p/DX1rEFEMBrg/",
      "commentsCount": 7,
      "dimensionsHeight": 1136,
      "dimensionsWidth": 640,
      "displayUrl": "https://scontent-dfw5-2.cdninstagram.com/v/t51.71878-15/684275477_834002319746688_7725607520898445231_n.jpg?stp=dst-jpg_e15_tt6&_nc_ht=scontent-dfw5-2.cdninstagram.com&_nc_cat=100&_nc_oc=Q6cZ2gFSXiroBSjRzB-WEaZ1ZzISmxmHU5fPU6J6gMFS78ccpZxaHTY6GRD0FqUDPOMDVQg&_nc_ohc=ADC5wBTmb5EQ7kNvwHh4v7Z&_nc_gid=D-zzd2bJFWa8pLO8E0JTRQ&edm=AOQ1c0wBAAAA&ccb=7-5&oh=00_Af5sdn8rv0foWoKfT7DhTWYUpOjEKVGUmBh6lMILJQdCcA&oe=6A204990&_nc_sid=8b3546",
      "videoUrl": "https://scontent-dfw5-1.cdninstagram.com/o1/v/t2/f2/m86/AQOkxjR9wB83J_ScZkcZHnuUL8fatdMubUDfQthou6WVrGBgDZ6Ha2h7nV78XgUDrApvs7i2IImenb_RuiMQOXk4D7UJmYr9in_Y6Oc.mp4?_nc_cat=105&_nc_sid=5e9851&_nc_ht=scontent-dfw5-1.cdninstagram.com&_nc_ohc=YAs14SxjeawQ7kNvwHXnPRS&efg=eyJ2ZW5jb2RlX3RhZyI6Inhwdl9wcm9ncmVzc2l2ZS5JTlNUQUdSQU0uQ0xJUFMuQzMuNzIwLmRhc2hfYmFzZWxpbmVfMV92MSIsInhwdl9hc3NldF9pZCI6MTYyMDMzNzg1OTA4MDUwMywiYXNzZXRfYWdlX2RheXMiOjI3LCJ2aV91c2VjYXNlX2lkIjoxMDA5OSwiZHVyYXRpb25fcyI6MjgsInVybGdlbl9zb3VyY2UiOiJ3d3cifQ%3D%3D&ccb=17-1&vs=1b594a4e80e43b51&_nc_vs=HBksFQIYUmlnX3hwdl9yZWVsc19wZXJtYW5lbnRfc3JfcHJvZC80MjRFRUNCMkRCQUU2OTk2RTI2MDA5MDAzQUNBNUQ5OV92aWRlb19kYXNoaW5pdC5tcDQVAALIARIAFQIYUWlnX3hwdl9wbGFjZW1lbnRfcGVybWFuZW50X3YyL0I3NEY2NDk1NzVGOTdEQjIyNUEzQUQwQUQ1ODJBMDg0X2F1ZGlvX2Rhc2hpbml0Lm1wNBUCAsgBEgAoABgAGwKIB3VzZV9vaWwBMRJwcm9ncmVzc2l2ZV9yZWNpcGUBMRUAACbuxI3oiezgBRUCKAJDMywXQDwiDEm6XjUYEmRhc2hfYmFzZWxpbmVfMV92MREAdf4HZeadAQA&_nc_gid=D-zzd2bJFWa8pLO8E0JTRQ&_nc_zt=28&_nc_ss=7a3ba&oh=00_Af5jQ94kQw1WR01Q1m2bNe7KqG9Iunx4KVfZzWyoIsJW9g&oe=6A1C5B4E",
      "likesCount": 228,
      "videoViewCount": 34996,
      "timestamp": "2026-05-02T13:57:17.000Z",
      "locationName": "The Sevens Stadium",
      "locationId": "236353357",
      "ownerUsername": "masihimtiaz_official",
      "ownerId": "41214192661",
      "productType": "clips",
      "taggedUsers": [
        {
          "full_name": "Imtiaz Developments",
          "id": "54725902033",
          "is_verified": true,
          "profile_pic_url": "https://scontent-dfw6-1.cdninstagram.com/v/t51.2885-19/447880441_1284319319210162_8460718414674929488_n.jpg?stp=dst-jpg_e0_s150x150_tt6&efg=eyJ2ZW5jb2RlX3RhZyI6InByb2ZpbGVfcGljLmRqYW5nby4xMDgwLmMyIn0&_nc_ht=scontent-dfw6-1.cdninstagram.com&_nc_cat=102&_nc_oc=Q6cZ2gFSXiroBSjRzB-WEaZ1ZzISmxmHU5fPU6J6gMFS78ccpZxaHTY6GRD0FqUDPOMDVQg&_nc_ohc=MJPDu0ke9DYQ7kNvwEDVhnH&_nc_gid=D-zzd2bJFWa8pLO8E0JTRQ&edm=AOQ1c0wBAAAA&ccb=7-5&oh=00_Af64WhrafhOCu1hFYeKhp4-7GZeCemH3SXRQP51vjdAjOA&oe=6A20526D&_nc_sid=8b3546",
          "username": "imtiazdevelopments"
        }
      ],
      "isCommentsDisabled": false
    },
    {
      "id": "3887311003952433602",
      "type": "Image",
      "shortCode": "DXygMMiDUnC",
      "caption": "Some gifts are priceless.",
      "url": "https://www.instagram.com/p/DXygMMiDUnC/",
      "commentsCount": 27,
      "dimensionsHeight": 942,
      "dimensionsWidth": 1080,
      "displayUrl": "https://scontent-dfw6-1.cdninstagram.com/v/t51.82787-15/684152477_18074583647368662_868127743335052552_n.jpg?stp=dst-jpg_e35_s1080x1080_sh2.08_tt6&_nc_ht=scontent-dfw6-1.cdninstagram.com&_nc_cat=106&_nc_oc=Q6cZ2gFSXiroBSjRzB-WEaZ1ZzISmxmHU5fPU6J6gMFS78ccpZxaHTY6GRD0FqUDPOMDVQg&_nc_ohc=zlBQJqE4EF8Q7kNvwH8tDMI&_nc_gid=D-zzd2bJFWa8pLO8E0JTRQ&edm=AOQ1c0wBAAAA&ccb=7-5&ig_cache_key=Mzg4NzMxMTAwMzk1MjQzMzYwMg%3D%3D.3-ccb7-5&oh=00_Af4lXmiolGbjdYXNKKEdSDcd9YpzD8Bo8SLS6NhQHGgl0Q&oe=6A204ABD&_nc_sid=8b3546",
      "likesCount": 995,
      "timestamp": "2026-05-01T08:20:25.000Z",
      "ownerUsername": "masihimtiaz_official",
      "ownerId": "41214192661",
      "isCommentsDisabled": false
    }
  ],
  "fbid": "17841441059851774"
}